LICENSE.txt
MANIFEST.in
README.md
pyproject.toml
setup.cfg
setup.py
verify_django_serializer/__init__.py
verify_django_serializer/decorators.py
verify_django_serializer/exceptions.py
verify_django_serializer.egg-info/PKG-INFO
verify_django_serializer.egg-info/SOURCES.txt
verify_django_serializer.egg-info/dependency_links.txt
verify_django_serializer.egg-info/not-zip-safe
verify_django_serializer.egg-info/requires.txt
verify_django_serializer.egg-info/top_level.txt