Metadata-Version: 2.1
Name: verify-django-serializer
Version: 1.0.dev0
Summary: Lib to make python packages
Home-page: https://gitlab.com/victorhdcoelho/verify_django_serializer
Author: Victor Coelho
Author-email: victorhdcoelho@gmail.com
License: UNKNOWN
Platform: UNKNOWN
Classifier: Programming Language :: Python :: 3
Classifier: Operating System :: OS Independent
Requires-Python: >=3.8
